MANIFEST.in
README.rst
setup.py
pysofia/__init__.py
pysofia/_sofia_ml.pyx
pysofia/compat.py
pysofia/datasets.py
pysofia/metrics.py
pysofia/misc.py
pysofia/sofia_ml.py
pysofia.egg-info/PKG-INFO
pysofia.egg-info/SOURCES.txt
pysofia.egg-info/dependency_links.txt
pysofia.egg-info/requires.txt
pysofia.egg-info/top_level.txt
pysofia/src/sf-data-set.cc
pysofia/src/sf-data-set.h
pysofia/src/sf-hash-inline.cc
pysofia/src/sf-hash-inline.h
pysofia/src/sf-hash-weight-vector.cc
pysofia/src/sf-hash-weight-vector.h
pysofia/src/sf-sparse-vector.cc
pysofia/src/sf-sparse-vector.h
pysofia/src/sf-weight-vector.cc
pysofia/src/sf-weight-vector.h
pysofia/src/sofia-ml-methods.cc
pysofia/src/sofia-ml-methods.h
pysofia/tests/__init__.py
pysofia/tests/run.py
pysofia/tests/test.py