Metadata-Version: 1.0
Name: pysofia
Version: 0.9
Summary: Python bindings for sofia-ml
Home-page: http://pypi.python.org/pypi/pysofia
Author: Fabian Pedregosa & Csy
Author-email: fabian@fseoane.net
License: UNKNOWN
Platform: UNKNOWN
